.gitignore
LICENSE
MANIFEST.in
README.rst
setup.py
etc/config.py
etc/httpd.conf
etc/test-config.py
etc/update.authenticate.sh
etc/websshkey.wsgi
gitolite_sshkey_form/__init__.py
gitolite_sshkey_form/app.py
gitolite_sshkey_form/dir.py
gitolite_sshkey_form/gitadmin.py
gitolite_sshkey_form/gitolite.py
gitolite_sshkey_form/identities.py
gitolite_sshkey_form/schema.sql
gitolite_sshkey_form/test-run.py
gitolite_sshkey_form/util.py
gitolite_sshkey_form/version.py
gitolite_sshkey_form/views.py
gitolite_sshkey_form.egg-info/PKG-INFO
gitolite_sshkey_form.egg-info/SOURCES.txt
gitolite_sshkey_form.egg-info/dependency_links.txt
gitolite_sshkey_form.egg-info/not-zip-safe
gitolite_sshkey_form.egg-info/requires.txt
gitolite_sshkey_form.egg-info/top_level.txt
gitolite_sshkey_form/static/css/logstyle.css
gitolite_sshkey_form/static/css/reset.css
gitolite_sshkey_form/static/css/style.css
gitolite_sshkey_form/static/css/custom-theme/jquery-ui-1.8.16.custom.css
gitolite_sshkey_form/static/css/custom-theme/images/ui-bg_flat_0_aaaaaa_40x100.png
gitolite_sshkey_form/static/css/custom-theme/images/ui-bg_flat_100_ffffff_40x100.png
gitolite_sshkey_form/static/css/custom-theme/images/ui-bg_flat_20_fbf9ee_40x100.png
gitolite_sshkey_form/static/css/custom-theme/images/ui-bg_flat_20_fcfcfc_40x100.png
gitolite_sshkey_form/static/css/custom-theme/images/ui-bg_inset-soft_95_fef1ec_1x100.png
gitolite_sshkey_form/static/css/custom-theme/images/ui-icons_222222_256x240.png
gitolite_sshkey_form/static/css/custom-theme/images/ui-icons_2e83ff_256x240.png
gitolite_sshkey_form/static/css/custom-theme/images/ui-icons_454545_256x240.png
gitolite_sshkey_form/static/css/custom-theme/images/ui-icons_888888_256x240.png
gitolite_sshkey_form/static/css/custom-theme/images/ui-icons_cd0a0a_256x240.png
gitolite_sshkey_form/static/images/buttonEnabled.png
gitolite_sshkey_form/static/images/commonIconsObjActEnabled.png
gitolite_sshkey_form/static/images/loading.gif
gitolite_sshkey_form/static/images/validationInputBg.png
gitolite_sshkey_form/static/images/sweetieplus/readme.txt
gitolite_sshkey_form/static/images/sweetieplus/with-shadows/warning-16.png
gitolite_sshkey_form/static/images/sweetieplus/without-shadows/minus-16-ns.png
