Metadata-Version: 1.1
Name: gitolite-sshkey-form
Version: 0.2.1
Summary: webapp for submitting ssh public keys directly to gitolite
Home-page: https://github.com/gvalkov/gitolite-sshkey-form
Author: Georgi Valkov
Author-email: georgi.t.valkov@gmail.com
License: New BSD License
Keywords: gitolite sshkey
Platform: UNKNOWN
Classifier: Programming Language :: Python
Classifier: License :: OSI Approved :: BSD License
Classifier: Topic :: Internet :: WWW/HTTP :: Dynamic Content :: CGI Tools/Libraries
Classifier: Topic :: Internet :: WWW/HTTP :: WSGI :: Application
Classifier: Development Status :: 4 - Beta
